motor/__init__.py
motor/controller.py
motorcontroller-0.0.1.dist-info/LICENSE
motorcontroller-0.0.1.dist-info/METADATA
motorcontroller-0.0.1.dist-info/WHEEL
motorcontroller-0.0.1.dist-info/top_level.txt
motorcontroller-0.0.1.dist-info/RECORD
